Metadata-Version: 1.0
Name: mleap-lregression
Version: 0.1
Summary: Linear Regression Estimator and Analysis
Home-page: UNKNOWN
Author: ['Anna Pastwa']
Author-email: UNKNOWN
License: UNKNOWN
Platform: UNKNOWN
